mongodbautomationaibi/__init__.py
mongodbautomationaibi/crud.py
mongodbautomationaibi-0.0.7.dist-info/METADATA
mongodbautomationaibi-0.0.7.dist-info/WHEEL
mongodbautomationaibi-0.0.7.dist-info/top_level.txt
mongodbautomationaibi-0.0.7.dist-info/RECORD
